snoparallel/__init__.py
snoparallel/managers.py
snoparallel/variables.py
snoparallel-1.3.0.dist-info/METADATA
snoparallel-1.3.0.dist-info/WHEEL
snoparallel-1.3.0.dist-info/RECORD
