Metadata-Version: 2.4
Name: SnoParallel
Version: 1.3.0
Summary: Simplified parallelism with Python.
License: MIT
Author: Max Snoodijk
Author-email: max_snoodijk@live.nl
Maintainer: Max Snoodijk
Maintainer-email: max_snoodijk@live.nl
Requires-Python: >=3.10,<3.13
Classifier: License :: OSI Approved :: MIT License
Classifier: Programming Language :: Python :: 3
Classifier: Programming Language :: Python :: 3.10
Classifier: Programming Language :: Python :: 3.11
Classifier: Programming Language :: Python :: 3.12
Requires-Dist: numpy (>=2.2,<3.0)
Project-URL: Documentation, https://thesecondsnomax.github.io/SnoParallel
Project-URL: Repository, https://dev.azure.com/snomax/snoparallel
